keyframed/__init__.py
keyframed/curve.py
keyframed/dsl.py
keyframed/interpolation.py
keyframed/misc.py
keyframed/serialization.py
keyframed/utils.py
keyframed-0.3.15.dist-info/METADATA
keyframed-0.3.15.dist-info/WHEEL
keyframed-0.3.15.dist-info/top_level.txt
keyframed-0.3.15.dist-info/RECORD
