Metadata-Version: 2.1
Name: keyframed
Version: 0.3.15
Author: David Marx
License: MIT
Requires-Dist: sortedcontainers
Requires-Dist: omegaconf
Requires-Dist: matplotlib
Provides-Extra: dev
Requires-Dist: pytest ; extra == 'dev'
Requires-Dist: loguru ; extra == 'dev'
